_feedforward_closedloop_learning.cp311-win_amd64.pyd
feedforward_closedloop_learning.py
feedforward_closedloop_learning-2.2.1.dist-info/LICENSE
feedforward_closedloop_learning-2.2.1.dist-info/METADATA
feedforward_closedloop_learning-2.2.1.dist-info/WHEEL
feedforward_closedloop_learning-2.2.1.dist-info/top_level.txt
feedforward_closedloop_learning-2.2.1.dist-info/RECORD
