Metadata-Version: 2.1
Name: feedforward-closedloop-learning
Version: 2.2.1
Summary: Feedforward Closedloop Learning (FCL)
Home-page: https://github.com/glasgowneuro/feedforward_closedloop_learning
Author: Bernd Porr, Paul Miller
Author-email: bernd@glasgowneuro.tech
License: GPL 3.0
Classifier: Intended Audience :: Developers
Classifier: Programming Language :: Python
License-File: LICENSE
Requires-Dist: numpy
